{
  "pid": 276,
  "cohort": "cohort_a",
  "age": 40,
  "is_female": false,
  "effects_bayesian": [
    {
      "action": "active_energy",
      "outcome": "deep_sleep",
      "nominal_step": 100.0,
      "dose_multiplier": 0.5149629932710894,
      "dose_multiplier_raw": 0.5149629932710894,
      "direction_conflict": false,
      "scaled_effect": 0.3361876068865442,
      "posterior": {
        "mean": 0.6528383811641522,
        "variance": 0.07550813384005566,
        "sd": 0.27478743391948557,
        "contraction": 0.014962993271089409,
        "prior_mean": 0.6921665440115441,
        "prior_variance": 0.07665512394382158,
        "source": "pop+cohort+user",
        "lam_js": 0.8768472906403941,
        "n_cohort": 534,
        "z_like": 2.3757941615169997
      },
      "cohort_prior": {
        "mean": 0.6984414526484751,
        "variance": 0.07805127404443395,
        "n": 534
      },
      "user_obs": {
        "slope": -0.007763819527505388,
        "se": 0.0061499177932012785,
        "n": 58,
        "at_nominal_step": -0.7763819527505388,
        "se_at_step": 0.6149917793201278,
        "residual_sd": 1.9483818994881876,
        "sigma_data_used": 12.0
      },
      "gate": {
        "score": 0.014962993271089409,
        "tier": "not_exposed"
      }
    },
    {
      "action": "bedtime",
      "outcome": "deep_sleep",
      "nominal_step": -0.5,
      "dose_multiplier": 0.7701238236606847,
      "dose_multiplier_raw": 0.7701238236606847,
      "direction_conflict": false,
      "scaled_effect": 0.35730867841043057,
      "posterior": {
        "mean": 0.463962634881245,
        "variance": 0.6894964437862106,
        "sd": 0.8303592257488385,
        "contraction": 0.27012382366068466,
        "prior_mean": 0.6072164646464647,
        "prior_variance": 0.9446759137205589,
        "source": "pop+cohort+user",
        "lam_js": 0.8768472906403941,
        "n_cohort": 534,
        "z_like": 0.5587492984892557
      },
      "cohort_prior": {
        "mean": 0.6056498876404495,
        "variance": 0.9560138510611396,
        "n": 534
      },
      "user_obs": {
        "slope": -0.18991316117470708,
        "se": 0.759046814466522,
        "n": 58,
        "at_nominal_step": 0.09495658058735354,
        "se_at_step": 0.379523407233261,
        "residual_sd": 1.9457069881544085,
        "sigma_data_used": 12.0
      },
      "gate": {
        "score": 0.27012382366068466,
        "tier": "not_exposed"
      }
    },
    {
      "action": "bedtime",
      "outcome": "sleep_quality",
      "nominal_step": -0.5,
      "dose_multiplier": 1.012598386808996,
      "dose_multiplier_raw": 1.012598386808996,
      "direction_conflict": false,
      "scaled_effect": 0.06352255884073456,
      "posterior": {
        "mean": 0.06273223389276114,
        "variance": 0.432277072457734,
        "sd": 0.6574778113805317,
        "contraction": 0.512598386808996,
        "prior_mean": 0.4607862962962966,
        "prior_variance": 0.8869011935098631,
        "source": "pop+cohort+user",
        "lam_js": 0.8768472906403941,
        "n_cohort": 534,
        "z_like": 0.09541346157528849
      },
      "cohort_prior": {
        "mean": 0.46373086142322145,
        "variance": 0.8849888909576128,
        "n": 534
      },
      "user_obs": {
        "slope": 0.6392422291662504,
        "se": 0.4292242520370906,
        "n": 58,
        "at_nominal_step": -0.3196211145831252,
        "se_at_step": 0.2146121260185453,
        "residual_sd": 1.1002544385366768,
        "sigma_data_used": 7.0
      },
      "gate": {
        "score": 0.512598386808996,
        "tier": "possible"
      }
    },
    {
      "action": "running_volume",
      "outcome": "hrv_daily",
      "nominal_step": 30.0,
      "dose_multiplier": 1.120246802740201,
      "dose_multiplier_raw": 1.120246802740201,
      "direction_conflict": false,
      "scaled_effect": 0.11186106239032399,
      "posterior": {
        "mean": 0.0998539447885092,
        "variance": 0.11451139444957417,
        "sd": 0.33839532273595946,
        "contraction": 0.620246802740201,
        "prior_mean": 0.14166006734006745,
        "prior_variance": 0.3015416203888705,
        "source": "pop+cohort+user",
        "lam_js": 0.8768472906403941,
        "n_cohort": 534,
        "z_like": 0.29508074751500774
      },
      "cohort_prior": {
        "mean": 0.13417902621722846,
        "variance": 0.24427088794406634,
        "n": 534
      },
      "user_obs": {
        "slope": 0.07009125104448942,
        "se": 0.21538295845623012,
        "n": 58,
        "at_nominal_step": 0.07009125104448942,
        "se_at_step": 0.21538295845623012,
        "residual_sd": 1.3404429660528534,
        "sigma_data_used": 3.5
      },
      "gate": {
        "score": 0.620246802740201,
        "tier": "possible"
      }
    },
    {
      "action": "sleep_duration",
      "outcome": "hrv_daily",
      "nominal_step": 0.5,
      "dose_multiplier": 0.5241850425609117,
      "dose_multiplier_raw": 0.5241850425609117,
      "direction_conflict": false,
      "scaled_effect": 0.07104753777493907,
      "posterior": {
        "mean": 0.13553904061786187,
        "variance": 0.0028627834485825698,
        "sd": 0.053504985268501566,
        "contraction": 0.024185042560911696,
        "prior_mean": 0.13540993265993234,
        "prior_variance": 0.0029337359780747863,
        "source": "pop+cohort+user",
        "lam_js": 0.8768472906403941,
        "n_cohort": 534,
        "z_like": 2.5332039610457353
      },
      "cohort_prior": {
        "mean": 0.13457651150347733,
        "variance": 0.002897733991751291,
        "n": 534
      },
      "user_obs": {
        "slope": 0.3962382545464207,
        "se": 0.610961094332802,
        "n": 58,
        "at_nominal_step": 0.19811912727321035,
        "se_at_step": 0.305480547166401,
        "residual_sd": 1.3404429660528538,
        "sigma_data_used": 3.5
      },
      "gate": {
        "score": 0.024185042560911696,
        "tier": "not_exposed"
      }
    },
    {
      "action": "training_load",
      "outcome": "hrv_daily",
      "nominal_step": 100.0,
      "dose_multiplier": 0.5,
      "dose_multiplier_raw": 1.4508966252752653,
      "direction_conflict": true,
      "scaled_effect": 0.8659770172524331,
      "posterior": {
        "mean": 1.7319540345048663,
        "variance": 0.20085509115264738,
        "sd": 0.44816859679438426,
        "contraction": 0.9508966252752653,
        "prior_mean": -5.056217651515151,
        "prior_variance": 4.090453910318943,
        "source": "pop+cohort+user",
        "lam_js": 0.8768472906403941,
        "n_cohort": 534,
        "z_like": 3.864514486050595
      },
      "cohort_prior": {
        "mean": -5.061554325842696,
        "variance": 4.099093150953106,
        "n": 534
      },
      "user_obs": {
        "slope": 0.020820485859804526,
        "se": 0.015801722004834293,
        "n": 58,
        "at_nominal_step": 2.0820485859804525,
        "se_at_step": 1.5801722004834293,
        "residual_sd": 1.3404429660528532,
        "sigma_data_used": 3.5
      },
      "gate": {
        "score": 0.47544831263763265,
        "tier": "possible"
      }
    },
    {
      "action": "training_load",
      "outcome": "resting_hr",
      "nominal_step": 100.0,
      "dose_multiplier": 0.5,
      "dose_multiplier_raw": 1.4165122067858007,
      "direction_conflict": true,
      "scaled_effect": -0.36278873083026986,
      "posterior": {
        "mean": -0.7255774616605397,
        "variance": 0.02275784878475381,
        "sd": 0.15085704751437307,
        "contraction": 0.9165122067858007,
        "prior_mean": 1.305251261157877,
        "prior_variance": 0.2725889367606766,
        "source": "pop+cohort+user",
        "lam_js": 0.8768472906403941,
        "n_cohort": 534,
        "z_like": -4.809702122742456
      },
      "cohort_prior": {
        "mean": 1.306352479669686,
        "variance": 0.273049088182262,
        "n": 534
      },
      "user_obs": {
        "slope": -0.009103612162578253,
        "se": 0.007619485527424514,
        "n": 58,
        "at_nominal_step": -0.9103612162578254,
        "se_at_step": 0.7619485527424514,
        "residual_sd": 0.6463527061831011,
        "sigma_data_used": 1.2
      },
      "gate": {
        "score": 0.45825610339290035,
        "tier": "possible"
      }
    }
  ],
  "tier_counts": {
    "recommended": 0,
    "possible": 4,
    "not_exposed": 3
  },
  "exposed_count": 4,
  "protocols": [
    {
      "protocol_id": "bedtime_p0276",
      "action": "bedtime",
      "target_value": 21.1037008065955,
      "current_value": 21.61,
      "delta": -0.506299193404498,
      "unit": "hr",
      "option_index": 0,
      "option_label": "single",
      "supporting_insight_ids": [
        "bedtime_sleep_quality"
      ],
      "outcomes_served": [
        "sleep_quality"
      ],
      "gate_tier": "possible",
      "weakest_contraction": 0.512598386808996,
      "horizon_days": 2,
      "description": "Shift bedtime earlier to 9:06pm",
      "rationale": "Optimizes sleep quality"
    },
    {
      "protocol_id": "running_volume_p0276",
      "action": "running_volume",
      "target_value": 2.9035801360735345,
      "current_value": 1.7833333333333334,
      "delta": 1.120246802740201,
      "unit": "km/day",
      "option_index": 0,
      "option_label": "single",
      "supporting_insight_ids": [
        "running_volume_hrv_daily"
      ],
      "outcomes_served": [
        "hrv_daily"
      ],
      "gate_tier": "possible",
      "weakest_contraction": 0.620246802740201,
      "horizon_days": 4,
      "description": "Increase daily running to 2.9 km/day",
      "rationale": "Optimizes HRV"
    },
    {
      "protocol_id": "training_load_p0276",
      "action": "training_load",
      "target_value": 164.988,
      "current_value": 114.988,
      "delta": 50.0,
      "unit": "TRIMP/day",
      "option_index": 0,
      "option_label": "collapsed",
      "supporting_insight_ids": [
        "training_load_hrv_daily",
        "training_load_resting_hr"
      ],
      "outcomes_served": [
        "hrv_daily",
        "resting_hr"
      ],
      "gate_tier": "possible",
      "weakest_contraction": 0.9165122067858007,
      "horizon_days": 4,
      "description": "Target training load ~165 TRIMP/day",
      "rationale": "Optimizes HRV and resting HR"
    }
  ],
  "current_values": {
    "bedtime": 21.61,
    "sleep_duration": 7.0566666666666675,
    "running_volume": 1.7833333333333334,
    "steps": 10408.8,
    "training_load": 114.988,
    "active_energy": 610.1519999999998
  },
  "behavioral_sds": {
    "bedtime": 0.38507363789842197,
    "sleep_duration": 0.35371452958495936,
    "running_volume": 0.9408732902029989,
    "steps": 1067.1811638470297,
    "training_load": 11.583296545218511,
    "active_energy": 47.80889082915892
  },
  "regime_activations": {
    "overreaching_state": 0.04750181553811808,
    "iron_deficiency_state": 2.1747282570575066e-05,
    "sleep_deprivation_state": 1.0,
    "inflammation_state": 0.9453186827840592
  },
  "release_schedule": [
    {
      "day": 7,
      "protocol_id": "bedtime_p0276",
      "framing": "initial"
    },
    {
      "day": 8,
      "protocol_id": "training_load_p0276",
      "framing": "initial"
    },
    {
      "day": 9,
      "protocol_id": "running_volume_p0276",
      "framing": "initial"
    },
    {
      "day": 21,
      "protocol_id": "bedtime_p0276",
      "framing": "adherence-check"
    },
    {
      "day": 22,
      "protocol_id": "training_load_p0276",
      "framing": "adherence-check"
    },
    {
      "day": 23,
      "protocol_id": "running_volume_p0276",
      "framing": "adherence-check"
    },
    {
      "day": 35,
      "protocol_id": "bedtime_p0276",
      "framing": "reinforcement"
    },
    {
      "day": 36,
      "protocol_id": "training_load_p0276",
      "framing": "reinforcement"
    },
    {
      "day": 37,
      "protocol_id": "running_volume_p0276",
      "framing": "reinforcement"
    }
  ]
}