{
  "pid": 622,
  "cohort": "cohort_b",
  "age": 35,
  "is_female": false,
  "effects_bayesian": [
    {
      "action": "active_energy",
      "outcome": "deep_sleep",
      "nominal_step": 100.0,
      "dose_multiplier": 0.5430024684482626,
      "dose_multiplier_raw": 0.5430024684482626,
      "direction_conflict": false,
      "scaled_effect": 0.3595459496190167,
      "posterior": {
        "mean": 0.6621442267960413,
        "variance": 0.07335876439502974,
        "sd": 0.27084823129389224,
        "contraction": 0.04300246844826261,
        "prior_mean": 0.6921665440115441,
        "prior_variance": 0.07665512394382158,
        "source": "pop+cohort+user",
        "lam_js": 0.8472505091649695,
        "n_cohort": 416,
        "z_like": 2.444705743998606
      },
      "cohort_prior": {
        "mean": 0.6841722046703297,
        "variance": 0.07489465690295352,
        "n": 416
      },
      "user_obs": {
        "slope": -0.0028560602169891308,
        "se": 0.007612946121103486,
        "n": 47,
        "at_nominal_step": -0.2856060216989131,
        "se_at_step": 0.7612946121103487,
        "residual_sd": 2.0390557784313503,
        "sigma_data_used": 12.0
      },
      "gate": {
        "score": 0.04300246844826261,
        "tier": "not_exposed"
      }
    },
    {
      "action": "bedtime",
      "outcome": "deep_sleep",
      "nominal_step": -0.5,
      "dose_multiplier": 0.7389205056675398,
      "dose_multiplier_raw": 0.7389205056675398,
      "direction_conflict": false,
      "scaled_effect": 0.3376697173868924,
      "posterior": {
        "mean": 0.4569770561203225,
        "variance": 0.7189734667224978,
        "sd": 0.8479230311310678,
        "contraction": 0.23892050566753975,
        "prior_mean": 0.6072164646464647,
        "prior_variance": 0.9446759137205589,
        "source": "pop+cohort+user",
        "lam_js": 0.8472505091649695,
        "n_cohort": 416,
        "z_like": 0.538936954585074
      },
      "cohort_prior": {
        "mean": 0.6215986538461539,
        "variance": 0.9384823525592582,
        "n": 416
      },
      "user_obs": {
        "slope": 0.1455081966548428,
        "se": 0.9412021092521213,
        "n": 47,
        "at_nominal_step": -0.0727540983274214,
        "se_at_step": 0.47060105462606067,
        "residual_sd": 2.0569534161671723,
        "sigma_data_used": 12.0
      },
      "gate": {
        "score": 0.23892050566753975,
        "tier": "not_exposed"
      }
    },
    {
      "action": "bedtime",
      "outcome": "sleep_quality",
      "nominal_step": -0.5,
      "dose_multiplier": 0.955773909065267,
      "dose_multiplier_raw": 0.955773909065267,
      "direction_conflict": false,
      "scaled_effect": 0.1750806228170959,
      "posterior": {
        "mean": 0.18318204876331287,
        "variance": 0.4826747695892219,
        "sd": 0.6947479899857372,
        "contraction": 0.45577390906526705,
        "prior_mean": 0.4607862962962966,
        "prior_variance": 0.8869011935098631,
        "source": "pop+cohort+user",
        "lam_js": 0.8472505091649695,
        "n_cohort": 416,
        "z_like": 0.2636668999460848
      },
      "cohort_prior": {
        "mean": 0.4770937500000001,
        "variance": 0.9009695161433738,
        "n": 416
      },
      "user_obs": {
        "slope": 0.30970267725347317,
        "se": 0.5598008122431544,
        "n": 47,
        "at_nominal_step": -0.15485133862673658,
        "se_at_step": 0.2799004061215772,
        "residual_sd": 1.223418627941328,
        "sigma_data_used": 7.0
      },
      "gate": {
        "score": 0.45577390906526705,
        "tier": "possible"
      }
    },
    {
      "action": "running_volume",
      "outcome": "hrv_daily",
      "nominal_step": 30.0,
      "dose_multiplier": 1.09643230454799,
      "dose_multiplier_raw": 1.09643230454799,
      "direction_conflict": false,
      "scaled_effect": 0.35165343578431824,
      "posterior": {
        "mean": 0.3207251686453084,
        "variance": 0.12169245682320128,
        "sd": 0.34884445935574393,
        "contraction": 0.59643230454799,
        "prior_mean": 0.14166006734006745,
        "prior_variance": 0.3015416203888705,
        "source": "pop+cohort+user",
        "lam_js": 0.8472505091649695,
        "n_cohort": 416,
        "z_like": 0.9193930419237071
      },
      "cohort_prior": {
        "mean": 0.11986480769230796,
        "variance": 0.2186938498312511,
        "n": 416
      },
      "user_obs": {
        "slope": 0.5462620010028348,
        "se": 0.3061303132501089,
        "n": 47,
        "at_nominal_step": 0.5462620010028348,
        "se_at_step": 0.3061303132501089,
        "residual_sd": 1.494176156587254,
        "sigma_data_used": 3.5
      },
      "gate": {
        "score": 0.59643230454799,
        "tier": "possible"
      }
    },
    {
      "action": "sleep_duration",
      "outcome": "hrv_daily",
      "nominal_step": 0.5,
      "dose_multiplier": 0.5035005851079042,
      "dose_multiplier_raw": 0.5035005851079042,
      "direction_conflict": false,
      "scaled_effect": 0.06517604173781232,
      "posterior": {
        "mean": 0.1294458113168718,
        "variance": 0.002923466185599415,
        "sd": 0.054069087153376424,
        "contraction": 0.003500585107904186,
        "prior_mean": 0.13540993265993234,
        "prior_variance": 0.0029337359780747863,
        "source": "pop+cohort+user",
        "lam_js": 0.8472505091649695,
        "n_cohort": 416,
        "z_like": 2.3940816857084366
      },
      "cohort_prior": {
        "mean": 0.13603296703296702,
        "variance": 0.002960794899166767,
        "n": 416
      },
      "user_obs": {
        "slope": -0.8856959101928822,
        "se": 0.9679198749973053,
        "n": 47,
        "at_nominal_step": -0.4428479550964411,
        "se_at_step": 0.4839599374986526,
        "residual_sd": 1.4941761565872567,
        "sigma_data_used": 3.5
      },
      "gate": {
        "score": 0.003500585107904186,
        "tier": "not_exposed"
      }
    },
    {
      "action": "training_load",
      "outcome": "hrv_daily",
      "nominal_step": 100.0,
      "dose_multiplier": 0.5,
      "dose_multiplier_raw": 1.4401193599846833,
      "direction_conflict": true,
      "scaled_effect": 2.0488440295835626,
      "posterior": {
        "mean": 4.097688059167125,
        "variance": 0.24493899810305306,
        "sd": 0.49491312177295627,
        "contraction": 0.9401193599846833,
        "prior_mean": -5.056217651515151,
        "prior_variance": 4.090453910318943,
        "source": "pop+cohort+user",
        "lam_js": 0.8472505091649695,
        "n_cohort": 416,
        "z_like": 8.27961086278686
      },
      "cohort_prior": {
        "mean": -5.038698533653847,
        "variance": 4.062157266087269,
        "n": 416
      },
      "user_obs": {
        "slope": 0.046834538414090285,
        "se": 0.02225011895241058,
        "n": 47,
        "at_nominal_step": 4.683453841409029,
        "se_at_step": 2.225011895241058,
        "residual_sd": 1.4941761565872576,
        "sigma_data_used": 3.5
      },
      "gate": {
        "score": 0.47005967999234166,
        "tier": "possible"
      }
    },
    {
      "action": "training_load",
      "outcome": "resting_hr",
      "nominal_step": 100.0,
      "dose_multiplier": 1.399007370925188,
      "dose_multiplier_raw": 1.399007370925188,
      "direction_conflict": false,
      "scaled_effect": 1.7377366242802865,
      "posterior": {
        "mean": 1.2421211355956552,
        "variance": 0.027529473380168392,
        "sd": 0.16592008130473054,
        "contraction": 0.899007370925188,
        "prior_mean": 1.305251261157877,
        "prior_variance": 0.2725889367606766,
        "source": "pop+cohort+user",
        "lam_js": 0.8472505091649695,
        "n_cohort": 416,
        "z_like": 7.486261613591923
      },
      "cohort_prior": {
        "mean": 1.3016362050919952,
        "variance": 0.2710810896650065,
        "n": 416
      },
      "user_obs": {
        "slope": 0.012353379113142087,
        "se": 0.010863853477152767,
        "n": 47,
        "at_nominal_step": 1.2353379113142087,
        "se_at_step": 1.0863853477152767,
        "residual_sd": 0.7295471484416761,
        "sigma_data_used": 1.2
      },
      "gate": {
        "score": 0.899007370925188,
        "tier": "recommended"
      }
    }
  ],
  "tier_counts": {
    "recommended": 1,
    "possible": 3,
    "not_exposed": 3
  },
  "exposed_count": 4,
  "protocols": [
    {
      "protocol_id": "bedtime_p0622",
      "action": "bedtime",
      "target_value": 20.362113045467368,
      "current_value": 20.84,
      "delta": -0.4778869545326323,
      "unit": "hr",
      "option_index": 0,
      "option_label": "single",
      "supporting_insight_ids": [
        "bedtime_sleep_quality"
      ],
      "outcomes_served": [
        "sleep_quality"
      ],
      "gate_tier": "possible",
      "weakest_contraction": 0.45577390906526705,
      "horizon_days": 2,
      "description": "Shift bedtime earlier to 8:22pm",
      "rationale": "Optimizes sleep quality"
    },
    {
      "protocol_id": "running_volume_p0622",
      "action": "running_volume",
      "target_value": 5.733098971214657,
      "current_value": 4.636666666666667,
      "delta": 1.0964323045479905,
      "unit": "km/day",
      "option_index": 0,
      "option_label": "single",
      "supporting_insight_ids": [
        "running_volume_hrv_daily"
      ],
      "outcomes_served": [
        "hrv_daily"
      ],
      "gate_tier": "possible",
      "weakest_contraction": 0.59643230454799,
      "horizon_days": 4,
      "description": "Increase daily running to 5.7 km/day",
      "rationale": "Optimizes HRV"
    },
    {
      "protocol_id": "training_load_conservative_p0622",
      "action": "training_load",
      "target_value": 142.50066666666663,
      "current_value": 92.50066666666665,
      "delta": 49.999999999999986,
      "unit": "TRIMP/day",
      "option_index": 0,
      "option_label": "conservative",
      "supporting_insight_ids": [
        "training_load_hrv_daily"
      ],
      "outcomes_served": [
        "hrv_daily"
      ],
      "gate_tier": "possible",
      "weakest_contraction": 0.9401193599846833,
      "horizon_days": 4,
      "description": "Target training load ~143 TRIMP/day",
      "rationale": "Optimizes HRV"
    },
    {
      "protocol_id": "training_load_aggressive_p0622",
      "action": "training_load",
      "target_value": 232.40140375918543,
      "current_value": 92.50066666666665,
      "delta": 139.9007370925188,
      "unit": "TRIMP/day",
      "option_index": 1,
      "option_label": "aggressive",
      "supporting_insight_ids": [
        "training_load_resting_hr"
      ],
      "outcomes_served": [
        "resting_hr"
      ],
      "gate_tier": "recommended",
      "weakest_contraction": 0.899007370925188,
      "horizon_days": 4,
      "description": "Target training load ~232 TRIMP/day",
      "rationale": "Optimizes resting HR"
    }
  ],
  "current_values": {
    "bedtime": 20.84,
    "sleep_duration": 7.006666666666666,
    "running_volume": 4.636666666666667,
    "steps": 10938.866666666667,
    "training_load": 92.50066666666665,
    "active_energy": 593.4546666666668
  },
  "behavioral_sds": {
    "bedtime": 0.45026353938772423,
    "sleep_duration": 0.32004901585385265,
    "running_volume": 0.768334077665413,
    "steps": 1004.8203636159325,
    "training_load": 11.080943274069101,
    "active_energy": 44.162850902575755
  },
  "regime_activations": {
    "overreaching_state": 0.058887792098904455,
    "iron_deficiency_state": 0.0007780044552516174,
    "sleep_deprivation_state": 1.0,
    "inflammation_state": 0.007033587154995153
  },
  "release_schedule": [
    {
      "day": 7,
      "protocol_id": "training_load_conservative_p0622",
      "framing": "initial"
    },
    {
      "day": 8,
      "protocol_id": "bedtime_p0622",
      "framing": "initial"
    },
    {
      "day": 9,
      "protocol_id": "training_load_aggressive_p0622",
      "framing": "initial"
    },
    {
      "day": 10,
      "protocol_id": "running_volume_p0622",
      "framing": "initial"
    },
    {
      "day": 21,
      "protocol_id": "training_load_conservative_p0622",
      "framing": "adherence-check"
    },
    {
      "day": 22,
      "protocol_id": "bedtime_p0622",
      "framing": "adherence-check"
    },
    {
      "day": 23,
      "protocol_id": "training_load_aggressive_p0622",
      "framing": "adherence-check"
    },
    {
      "day": 24,
      "protocol_id": "running_volume_p0622",
      "framing": "adherence-check"
    },
    {
      "day": 35,
      "protocol_id": "training_load_conservative_p0622",
      "framing": "reinforcement"
    },
    {
      "day": 36,
      "protocol_id": "bedtime_p0622",
      "framing": "reinforcement"
    },
    {
      "day": 37,
      "protocol_id": "training_load_aggressive_p0622",
      "framing": "reinforcement"
    },
    {
      "day": 38,
      "protocol_id": "running_volume_p0622",
      "framing": "reinforcement"
    }
  ]
}