{
  "pid": 612,
  "cohort": "cohort_b",
  "age": 34,
  "is_female": false,
  "effects_bayesian": [
    {
      "action": "active_energy",
      "outcome": "deep_sleep",
      "nominal_step": 100.0,
      "dose_multiplier": 0.5430024684482626,
      "dose_multiplier_raw": 0.5430024684482626,
      "direction_conflict": false,
      "scaled_effect": 0.36748988435123625,
      "posterior": {
        "mean": 0.6767738743461178,
        "variance": 0.07335876439502974,
        "sd": 0.27084823129389224,
        "contraction": 0.04300246844826261,
        "prior_mean": 0.6921665440115441,
        "prior_variance": 0.07665512394382158,
        "source": "pop+cohort+user",
        "lam_js": 0.8472505091649695,
        "n_cohort": 416,
        "z_like": 2.498719932978862
      },
      "cohort_prior": {
        "mean": 0.6841722046703297,
        "variance": 0.07489465690295352,
        "n": 416
      },
      "user_obs": {
        "slope": 0.003254014061156288,
        "se": 0.007119189925748812,
        "n": 47,
        "at_nominal_step": 0.3254014061156288,
        "se_at_step": 0.7119189925748812,
        "residual_sd": 2.2086720076473627,
        "sigma_data_used": 12.0
      },
      "gate": {
        "score": 0.04300246844826261,
        "tier": "not_exposed"
      }
    },
    {
      "action": "bedtime",
      "outcome": "deep_sleep",
      "nominal_step": -0.5,
      "dose_multiplier": 0.7389205056675398,
      "dose_multiplier_raw": 0.7389205056675398,
      "direction_conflict": false,
      "scaled_effect": 0.5253332690848523,
      "posterior": {
        "mean": 0.7109469355032542,
        "variance": 0.7189734667224978,
        "sd": 0.8479230311310678,
        "contraction": 0.23892050566753975,
        "prior_mean": 0.6072164646464647,
        "prior_variance": 0.9446759137205589,
        "source": "pop+cohort+user",
        "lam_js": 0.8472505091649695,
        "n_cohort": 416,
        "z_like": 0.8384569228587913
      },
      "cohort_prior": {
        "mean": 0.6215986538461539,
        "variance": 0.9384823525592582,
        "n": 416
      },
      "user_obs": {
        "slope": -2.0190236463929727,
        "se": 0.9688061278147598,
        "n": 47,
        "at_nominal_step": 1.0095118231964864,
        "se_at_step": 0.4844030639073799,
        "residual_sd": 2.2324075461587403,
        "sigma_data_used": 12.0
      },
      "gate": {
        "score": 0.23892050566753975,
        "tier": "not_exposed"
      }
    },
    {
      "action": "bedtime",
      "outcome": "sleep_quality",
      "nominal_step": -0.5,
      "dose_multiplier": 0.955773909065267,
      "dose_multiplier_raw": 0.955773909065267,
      "direction_conflict": false,
      "scaled_effect": 0.3008129180732689,
      "posterior": {
        "mean": 0.3147322972725417,
        "variance": 0.4826747695892219,
        "sd": 0.6947479899857372,
        "contraction": 0.45577390906526705,
        "prior_mean": 0.4607862962962966,
        "prior_variance": 0.8869011935098631,
        "source": "pop+cohort+user",
        "lam_js": 0.8472505091649695,
        "n_cohort": 416,
        "z_like": 0.4530164920362029
      },
      "cohort_prior": {
        "mean": 0.4770937500000001,
        "variance": 0.9009695161433738,
        "n": 416
      },
      "user_obs": {
        "slope": -0.25858114475460275,
        "se": 0.46227203961637964,
        "n": 47,
        "at_nominal_step": 0.12929057237730138,
        "se_at_step": 0.23113601980818982,
        "residual_sd": 1.0652075373898926,
        "sigma_data_used": 7.0
      },
      "gate": {
        "score": 0.45577390906526705,
        "tier": "possible"
      }
    },
    {
      "action": "running_volume",
      "outcome": "hrv_daily",
      "nominal_step": 30.0,
      "dose_multiplier": 1.09643230454799,
      "dose_multiplier_raw": 1.09643230454799,
      "direction_conflict": false,
      "scaled_effect": 0.12279236925259218,
      "posterior": {
        "mean": 0.11199265904812425,
        "variance": 0.12169245682320128,
        "sd": 0.34884445935574393,
        "contraction": 0.59643230454799,
        "prior_mean": 0.14166006734006745,
        "prior_variance": 0.3015416203888705,
        "source": "pop+cohort+user",
        "lam_js": 0.8472505091649695,
        "n_cohort": 416,
        "z_like": 0.3210389502959443
      },
      "cohort_prior": {
        "mean": 0.11986480769230796,
        "variance": 0.2186938498312511,
        "n": 416
      },
      "user_obs": {
        "slope": 0.09920318213888947,
        "se": 0.2856062381765179,
        "n": 47,
        "at_nominal_step": 0.09920318213888947,
        "se_at_step": 0.2856062381765179,
        "residual_sd": 1.338780089390253,
        "sigma_data_used": 3.5
      },
      "gate": {
        "score": 0.59643230454799,
        "tier": "possible"
      }
    },
    {
      "action": "sleep_duration",
      "outcome": "hrv_daily",
      "nominal_step": 0.5,
      "dose_multiplier": 0.5035005851079042,
      "dose_multiplier_raw": 0.5035005851079042,
      "direction_conflict": false,
      "scaled_effect": 0.06645216912642737,
      "posterior": {
        "mean": 0.13198032155650055,
        "variance": 0.002923466185599415,
        "sd": 0.054069087153376424,
        "contraction": 0.003500585107904186,
        "prior_mean": 0.13540993265993234,
        "prior_variance": 0.0029337359780747863,
        "source": "pop+cohort+user",
        "lam_js": 0.8472505091649695,
        "n_cohort": 416,
        "z_like": 2.440957088513725
      },
      "cohort_prior": {
        "mean": 0.13603296703296702,
        "variance": 0.002960794899166767,
        "n": 416
      },
      "user_obs": {
        "slope": -0.43377316311215314,
        "se": 1.0354638426057452,
        "n": 47,
        "at_nominal_step": -0.21688658155607657,
        "se_at_step": 0.5177319213028726,
        "residual_sd": 1.3387800893902533,
        "sigma_data_used": 3.5
      },
      "gate": {
        "score": 0.003500585107904186,
        "tier": "not_exposed"
      }
    },
    {
      "action": "training_load",
      "outcome": "hrv_daily",
      "nominal_step": 100.0,
      "dose_multiplier": 0.5,
      "dose_multiplier_raw": 1.4401193599846833,
      "direction_conflict": true,
      "scaled_effect": 0.5264196283488747,
      "posterior": {
        "mean": 1.0528392566977494,
        "variance": 0.24493899810305306,
        "sd": 0.49491312177295627,
        "contraction": 0.9401193599846833,
        "prior_mean": -5.056217651515151,
        "prior_variance": 4.090453910318943,
        "source": "pop+cohort+user",
        "lam_js": 0.8472505091649695,
        "n_cohort": 416,
        "z_like": 2.1273213628406165
      },
      "cohort_prior": {
        "mean": -5.038698533653847,
        "variance": 4.062157266087269,
        "n": 416
      },
      "user_obs": {
        "slope": 0.014434462668685318,
        "se": 0.018327286136409826,
        "n": 47,
        "at_nominal_step": 1.4434462668685317,
        "se_at_step": 1.8327286136409826,
        "residual_sd": 1.3387800893902542,
        "sigma_data_used": 3.5
      },
      "gate": {
        "score": 0.47005967999234166,
        "tier": "possible"
      }
    },
    {
      "action": "training_load",
      "outcome": "resting_hr",
      "nominal_step": 100.0,
      "dose_multiplier": 1.399007370925188,
      "dose_multiplier_raw": 1.399007370925188,
      "direction_conflict": false,
      "scaled_effect": 0.6519321144786161,
      "posterior": {
        "mean": 0.4659961970375338,
        "variance": 0.027529473380168392,
        "sd": 0.16592008130473054,
        "contraction": 0.899007370925188,
        "prior_mean": 1.305251261157877,
        "prior_variance": 0.2725889367606766,
        "source": "pop+cohort+user",
        "lam_js": 0.8472505091649695,
        "n_cohort": 416,
        "z_like": 2.808558152654713
      },
      "cohort_prior": {
        "mean": 1.3016362050919952,
        "variance": 0.2710810896650065,
        "n": 416
      },
      "user_obs": {
        "slope": 0.003715674088669812,
        "se": 0.009453803928500116,
        "n": 47,
        "at_nominal_step": 0.3715674088669812,
        "se_at_step": 0.9453803928500115,
        "residual_sd": 0.6905858496600437,
        "sigma_data_used": 1.2
      },
      "gate": {
        "score": 0.899007370925188,
        "tier": "recommended"
      }
    }
  ],
  "tier_counts": {
    "recommended": 1,
    "possible": 3,
    "not_exposed": 3
  },
  "exposed_count": 4,
  "protocols": [
    {
      "protocol_id": "bedtime_p0612",
      "action": "bedtime",
      "target_value": 22.005446378800706,
      "current_value": 22.483333333333338,
      "delta": -0.4778869545326323,
      "unit": "hr",
      "option_index": 0,
      "option_label": "single",
      "supporting_insight_ids": [
        "bedtime_sleep_quality"
      ],
      "outcomes_served": [
        "sleep_quality"
      ],
      "gate_tier": "possible",
      "weakest_contraction": 0.45577390906526705,
      "horizon_days": 2,
      "description": "Shift bedtime earlier to 10:00pm",
      "rationale": "Optimizes sleep quality"
    },
    {
      "protocol_id": "running_volume_p0612",
      "action": "running_volume",
      "target_value": 2.823098971214657,
      "current_value": 1.7266666666666668,
      "delta": 1.0964323045479902,
      "unit": "km/day",
      "option_index": 0,
      "option_label": "single",
      "supporting_insight_ids": [
        "running_volume_hrv_daily"
      ],
      "outcomes_served": [
        "hrv_daily"
      ],
      "gate_tier": "possible",
      "weakest_contraction": 0.59643230454799,
      "horizon_days": 4,
      "description": "Increase daily running to 2.8 km/day",
      "rationale": "Optimizes HRV"
    },
    {
      "protocol_id": "training_load_conservative_p0612",
      "action": "training_load",
      "target_value": 150.45133333333334,
      "current_value": 100.45133333333334,
      "delta": 50.0,
      "unit": "TRIMP/day",
      "option_index": 0,
      "option_label": "conservative",
      "supporting_insight_ids": [
        "training_load_hrv_daily"
      ],
      "outcomes_served": [
        "hrv_daily"
      ],
      "gate_tier": "possible",
      "weakest_contraction": 0.9401193599846833,
      "horizon_days": 4,
      "description": "Target training load ~150 TRIMP/day",
      "rationale": "Optimizes HRV"
    },
    {
      "protocol_id": "training_load_aggressive_p0612",
      "action": "training_load",
      "target_value": 240.35207042585213,
      "current_value": 100.45133333333334,
      "delta": 139.9007370925188,
      "unit": "TRIMP/day",
      "option_index": 1,
      "option_label": "aggressive",
      "supporting_insight_ids": [
        "training_load_resting_hr"
      ],
      "outcomes_served": [
        "resting_hr"
      ],
      "gate_tier": "recommended",
      "weakest_contraction": 0.899007370925188,
      "horizon_days": 4,
      "description": "Target training load ~240 TRIMP/day",
      "rationale": "Optimizes resting HR"
    }
  ],
  "current_values": {
    "bedtime": 22.483333333333338,
    "sleep_duration": 6.956666666666668,
    "running_volume": 1.7266666666666668,
    "steps": 5926.166666666667,
    "training_load": 100.45133333333334,
    "active_energy": 406.3466666666667
  },
  "behavioral_sds": {
    "bedtime": 0.46500152160432723,
    "sleep_duration": 0.20649820685410866,
    "running_volume": 0.7501129661022697,
    "steps": 1094.7271464420862,
    "training_load": 12.636229529237887,
    "active_energy": 49.13809205256181
  },
  "regime_activations": {
    "overreaching_state": 0.03952070419904081,
    "iron_deficiency_state": 0.5523079095743253,
    "sleep_deprivation_state": 1.0,
    "inflammation_state": 0.0024726231566347743
  },
  "release_schedule": [
    {
      "day": 7,
      "protocol_id": "training_load_conservative_p0612",
      "framing": "initial"
    },
    {
      "day": 8,
      "protocol_id": "bedtime_p0612",
      "framing": "initial"
    },
    {
      "day": 9,
      "protocol_id": "training_load_aggressive_p0612",
      "framing": "initial"
    },
    {
      "day": 10,
      "protocol_id": "running_volume_p0612",
      "framing": "initial"
    },
    {
      "day": 21,
      "protocol_id": "training_load_conservative_p0612",
      "framing": "adherence-check"
    },
    {
      "day": 22,
      "protocol_id": "bedtime_p0612",
      "framing": "adherence-check"
    },
    {
      "day": 23,
      "protocol_id": "training_load_aggressive_p0612",
      "framing": "adherence-check"
    },
    {
      "day": 24,
      "protocol_id": "running_volume_p0612",
      "framing": "adherence-check"
    },
    {
      "day": 35,
      "protocol_id": "training_load_conservative_p0612",
      "framing": "reinforcement"
    },
    {
      "day": 36,
      "protocol_id": "bedtime_p0612",
      "framing": "reinforcement"
    },
    {
      "day": 37,
      "protocol_id": "training_load_aggressive_p0612",
      "framing": "reinforcement"
    },
    {
      "day": 38,
      "protocol_id": "running_volume_p0612",
      "framing": "reinforcement"
    }
  ]
}